pond/__init__.py
pond/count_min_sketch.py
pond/pond_class.py
pond/pooled_object.py
pond/pooled_object_factory.py
pond/py.typed
pondpond-1.3.3.dist-info/WHEEL
pondpond-1.3.3.dist-info/METADATA
pondpond-1.3.3.dist-info/licenses/LICENSE
pondpond-1.3.3.dist-info/RECORD
