Metadata-Version: 2.1
Name: pondpond
Version: 1.3.3
Summary: Pond is a high performance object-pooling library for Python.
Author-email: Andy Qin <dr.qin@protonmail.com>
Requires-Python: >=3.8
Requires-Dist: madoka>=0.7.1
Project-URL: Blog, https://qin.news
Project-URL: Bug Tracker, https://github.com/t-baby/pond/issues
Project-URL: Homepage, https://github.com/t-baby/pond
